space_exploration_common_lib/__init__.py
space_exploration_common_lib/model/Astronaut.py
space_exploration_common_lib/model/Duration.py
space_exploration_common_lib/model/Mission.py
space_exploration_common_lib/model/Orbit.py
space_exploration_common_lib/model/Program.py
space_exploration_common_lib/model/__init__.py
space_exploration_common_lib-0.0.59.dist-info/METADATA
space_exploration_common_lib-0.0.59.dist-info/WHEEL
space_exploration_common_lib-0.0.59.dist-info/top_level.txt
space_exploration_common_lib-0.0.59.dist-info/RECORD
