Metadata-Version: 2.1
Name: space-exploration-common-lib
Version: 0.0.59
Summary: A common library for space exploration projects
Author: Steven Hatch
Author-email: stevegreghatch@gmail.com
Requires-Python: >=3.12, <4
Requires-Dist: pydantic ==2.8.2
